dataengtools/__init__.py
dataengtools/core/__init__.py
dataengtools/core/interfaces/__init__.py
dataengtools/core/interfaces/engine_layer/__init__.py
dataengtools/core/interfaces/engine_layer/catalog.py
dataengtools/core/interfaces/engine_layer/filesystem.py
dataengtools/core/interfaces/engine_layer/sql.py
dataengtools/core/interfaces/integration_layer/__init__.py
dataengtools/core/interfaces/integration_layer/catalog_metadata.py
dataengtools/core/interfaces/integration_layer/catalog_partitions.py
dataengtools/core/interfaces/integration_layer/filesystem_handler.py
dataengtools/core/interfaces/integration_layer/sql_configurator.py
dataengtools/core/interfaces/io/__init__.py
dataengtools/core/interfaces/io/reader.py
dataengtools/core/interfaces/io/writer.py
dataengtools/engine_factory.py
dataengtools/engines/__init__.py
dataengtools/engines/catalog_engine.py
dataengtools/engines/filesystem_engine.py
dataengtools/engines/sql_engine.py
dataengtools/io/__init__.py
dataengtools/io/duckdb_io/__init__.py
dataengtools/io/duckdb_io/reader.py
dataengtools/io/duckdb_io/string_builder.py
dataengtools/io/duckdb_io/writer.py
dataengtools/providers/__init__.py
dataengtools/providers/aws/__init__.py
dataengtools/providers/aws/glue_catalog_metadata_handler.py
dataengtools/providers/aws/glue_catalog_partitions_handler.py
dataengtools/providers/aws/glue_sql_provider_configurator.py
dataengtools/providers/aws/s3_filesystem_handler.py
dataengtools/providers/local/__init__.py
dataengtools/utils/__init__.py
dataengtools/utils/logger.py
dataengtools/utils/partition_helper.py
dataengtools-0.1.0.dist-info/METADATA
dataengtools-0.1.0.dist-info/WHEEL
dataengtools-0.1.0.dist-info/RECORD
