Metadata-Version: 2.3
Name: dataengtools
Version: 0.1.0
Summary: 
Author: Guilherme Magalhaes
Requires-Python: >=3.9,<4.0
Classifier: Programming Language :: Python :: 3
Classifier: Programming Language :: Python :: 3.9
Classifier: Programming Language :: Python :: 3.10
Classifier: Programming Language :: Python :: 3.11
Classifier: Programming Language :: Python :: 3.12
Classifier: Programming Language :: Python :: 3.13
Requires-Dist: boto3 (==1.35.76)
Requires-Dist: boto3-stubs[glue,s3] (>=1.35.90,<2.0.0)
Requires-Dist: duckdb (>=1.1.3,<2.0.0)
Requires-Dist: mypy-boto3 (==1.35.70)
Requires-Dist: pandas (==2.2.3)
Requires-Dist: polars (==1.16.0)
Requires-Dist: pyarrow (>=18.1.0,<19.0.0)
Requires-Dist: s3fs (>=2024.12.0,<2025.0.0)
